ais_dom-0.79.5.dist-info/LICENSE.txt
ais_dom-0.79.5.dist-info/METADATA
ais_dom-0.79.5.dist-info/RECORD
ais_dom-0.79.5.dist-info/WHEEL
ais_dom-0.79.5.dist-info/entry_points.txt
ais_dom-0.79.5.dist-info/top_level.txt
homeassistant/__init__.py
homeassistant/__main__.py
homeassistant/bootstrap.py
homeassistant/config.py
homeassistant/config_entries.py
homeassistant/const.py
homeassistant/core.py
homeassistant/data_entry_flow.py
homeassistant/exceptions.py
homeassistant/loader.py
homeassistant/monkey_patch.py
homeassistant/package_constraints.txt
homeassistant/requirements.py
homeassistant/setup.py
homeassistant/ais-dom-config/automations.yaml
homeassistant/ais-dom-config/configuration.yaml
homeassistant/ais-dom-config/customize.yaml
homeassistant/ais-dom-config/mqtt.yaml
homeassistant/ais-dom-config/scripts.yaml
homeassistant/ais-dom-config/ais_packages/main_ais_config.yaml
homeassistant/ais-dom-config/ais_packages/main_ais_groups.yaml
homeassistant/ais-dom-config/ais_packages/daily_bootstrap/bootstrap.sh
homeassistant/ais-dom-config/ais_packages/virtual_devices/airly_widget.yaml
homeassistant/ais-dom-config/ais_packages/virtual_devices/ais_bookmarks.yaml
homeassistant/ais-dom-config/ais_packages/virtual_devices/ais_books_player.yaml
homeassistant/ais-dom-config/ais_packages/virtual_devices/ais_cloud.yaml
homeassistant/ais-dom-config/ais_packages/virtual_devices/ais_day.yaml
homeassistant/ais-dom-config/ais_packages/virtual_devices/ais_dev.yaml
homeassistant/ais-dom-config/ais_packages/virtual_devices/ais_drives.yaml
homeassistant/ais-dom-config/ais_packages/virtual_devices/ais_help.yaml
homeassistant/ais-dom-config/ais_packages/virtual_devices/ais_knowledge.yaml
homeassistant/ais-dom-config/ais_packages/virtual_devices/ais_music_player.yaml
homeassistant/ais-dom-config/ais_packages/virtual_devices/ais_news.yaml
homeassistant/ais-dom-config/ais_packages/virtual_devices/ais_podcast_player.yaml
homeassistant/ais-dom-config/ais_packages/virtual_devices/ais_radio_player.yaml
homeassistant/ais-dom-config/ais_packages/virtual_devices/ais_sensors.yaml
homeassistant/ais-dom-config/ais_packages/virtual_devices/ais_weather.yaml
